{"train_loss": 1.4212131638025947e-06, "test_loss": 4.295250920607698e-06, "train_acc": 1.0, "test_acc": 1.0, "all_loss": 3.4330808753495167e-06, "percent_x_embed_trivial_rep": 1.0101071893586777e-05, "percent_y_embed_trivial_rep": 1.1138843547087163e-05, "percent_unembed_trivial_rep": 0.006404695566743612, "percent_hidden_x_trivial_rep": 3.892081664282673e-15, "percent_hidden_y_trivial_rep": 3.892081664282673e-15, "percent_hidden_xy_trivial_rep": 3.892081664282673e-15, "total_percent_hidden_trivial_rep": 1.1676244992848018e-14, "hidden_excluded_loss_trivial_rep": 1.4390863610127102e-06, "hidden_restricted_loss_trivial_rep": 4.776748703570972, "logit_sign_rep_trace_similarity": 0.3279299736022949, "logit_excluded_loss_sign_rep": 4.5377697514082845e-05, "logit_restricted_loss_sign_rep": 4.084821482707703, "percent_x_embed_sign_rep": 0.04629944637417793, "percent_y_embed_sign_rep": 0.0467347651720047, "percent_unembed_sign_rep": 0.06677478551864624, "percent_hidden_x_sign_rep": 0.017141299322247505, "percent_hidden_y_sign_rep": 0.01713939756155014, "percent_hidden_xy_sign_rep": 0.017113961279392242, "total_percent_hidden_sign_rep": 0.05139465630054474, "hidden_excluded_loss_sign_rep": 4.562178670651798e-05, "hidden_restricted_loss_sign_rep": 4.085699295399746, "logit_freq_1_rep_trace_similarity": 7.71597697166726e-05, "logit_excluded_loss_freq_1_rep": 1.4228794897923095e-06, "logit_restricted_loss_freq_1_rep": 4.769527518690051, "percent_x_embed_freq_1_rep": 1.006083402899094e-05, "percent_y_embed_freq_1_rep": 1.6253648936981335e-05, "percent_unembed_freq_1_rep": 0.0002564482856541872, "percent_hidden_x_freq_1_rep": 1.0201612894888967e-05, "percent_hidden_y_freq_1_rep": 1.7030659364536405e-05, "percent_hidden_xy_freq_1_rep": 6.707708052999806e-06, "total_percent_hidden_freq_1_rep": 3.393998122191988e-05, "hidden_excluded_loss_freq_1_rep": 1.42273506797538e-06, "hidden_restricted_loss_freq_1_rep": 4.769604534495571, "logit_freq_2_rep_trace_similarity": 0.001073201885446906, "logit_excluded_loss_freq_2_rep": 1.4461786508640321e-06, "logit_restricted_loss_freq_2_rep": 4.754620698396542, "percent_x_embed_freq_2_rep": 8.386646368307993e-05, "percent_y_embed_freq_2_rep": 1.109873664972838e-05, "percent_unembed_freq_2_rep": 0.0005322288488969207, "percent_hidden_x_freq_2_rep": 3.260727316956036e-05, "percent_hidden_y_freq_2_rep": 6.3050938479136676e-06, "percent_hidden_xy_freq_2_rep": 0.0001863122161012143, "total_percent_hidden_freq_2_rep": 0.00022522459039464593, "hidden_excluded_loss_freq_2_rep": 1.446387150698037e-06, "hidden_restricted_loss_freq_2_rep": 4.754948602944254, "logit_freq_3_rep_trace_similarity": 5.788677299278788e-06, "logit_excluded_loss_freq_3_rep": 1.4213695316214477e-06, "logit_restricted_loss_freq_3_rep": 4.770597804505267, "percent_x_embed_freq_3_rep": 1.2187349057057872e-05, "percent_y_embed_freq_3_rep": 1.2667493137996644e-05, "percent_unembed_freq_3_rep": 0.0002552718506194651, "percent_hidden_x_freq_3_rep": 6.720685178152053e-06, "percent_hidden_y_freq_3_rep": 6.803986707382137e-06, "percent_hidden_xy_freq_3_rep": 1.099564087780891e-06, "total_percent_hidden_freq_3_rep": 1.4624236428062432e-05, "hidden_excluded_loss_freq_3_rep": 1.4213817787466918e-06, "hidden_restricted_loss_freq_3_rep": 4.770611278368727, "logit_freq_4_rep_trace_similarity": 5.9322053857613355e-05, "logit_excluded_loss_freq_4_rep": 1.4224840987817873e-06, "logit_restricted_loss_freq_4_rep": 4.769794987483173, "percent_x_embed_freq_4_rep": 1.0093637683894485e-05, "percent_y_embed_freq_4_rep": 9.04991065908689e-06, "percent_unembed_freq_4_rep": 0.0002517518005333841, "percent_hidden_x_freq_4_rep": 2.0586927348631434e-05, "percent_hidden_y_freq_4_rep": 9.083327313419431e-06, "percent_hidden_xy_freq_4_rep": 1.0487697181815747e-05, "total_percent_hidden_freq_4_rep": 4.0157952753361315e-05, "hidden_excluded_loss_freq_4_rep": 1.4225106748640688e-06, "hidden_restricted_loss_freq_4_rep": 4.769865275358696, "logit_freq_5_rep_trace_similarity": 0.0019673516508191824, "logit_excluded_loss_freq_5_rep": 1.4802614010022043e-06, "logit_restricted_loss_freq_5_rep": 4.741286327978392, "percent_x_embed_freq_5_rep": 0.0001227679313160479, "percent_y_embed_freq_5_rep": 3.335900328238495e-05, "percent_unembed_freq_5_rep": 0.0013768903445452452, "percent_hidden_x_freq_5_rep": 4.70244194730185e-05, "percent_hidden_y_freq_5_rep": 1.3609727830043994e-05, "percent_hidden_xy_freq_5_rep": 0.00017691853281576186, "total_percent_hidden_freq_5_rep": 0.00023755268193781376, "hidden_excluded_loss_freq_5_rep": 1.4799310831764238e-06, "hidden_restricted_loss_freq_5_rep": 4.741795396785382, "logit_freq_6_rep_trace_similarity": 0.24446478486061096, "logit_excluded_loss_freq_6_rep": 0.00019191974702768375, "logit_restricted_loss_freq_6_rep": 2.661600097722514, "percent_x_embed_freq_6_rep": 0.12333348393440247, "percent_y_embed_freq_6_rep": 0.12506356835365295, "percent_unembed_freq_6_rep": 0.15825212001800537, "percent_hidden_x_freq_6_rep": 0.04563117027282715, "percent_hidden_y_freq_6_rep": 0.0458587147295475, "percent_hidden_xy_freq_6_rep": 0.01605881378054619, "total_percent_hidden_freq_6_rep": 0.10754869878292084, "hidden_excluded_loss_freq_6_rep": 0.00019274527475591545, "hidden_restricted_loss_freq_6_rep": 2.6637429540781223, "logit_freq_7_rep_trace_similarity": 0.0069529348984360695, "logit_excluded_loss_freq_7_rep": 1.5784627054814033e-06, "logit_restricted_loss_freq_7_rep": 4.667761089355573, "percent_x_embed_freq_7_rep": 3.1536081223748624e-05, "percent_y_embed_freq_7_rep": 1.8859573174268007e-05, "percent_unembed_freq_7_rep": 0.005654158070683479, "percent_hidden_x_freq_7_rep": 0.0010682353749871254, "percent_hidden_y_freq_7_rep": 0.0010489417472854257, "percent_hidden_xy_freq_7_rep": 0.00039101086440496147, "total_percent_hidden_freq_7_rep": 0.002508187899366021, "hidden_excluded_loss_freq_7_rep": 1.578581856647622e-06, "hidden_restricted_loss_freq_7_rep": 4.668165686292015, "logit_freq_8_rep_trace_similarity": 3.4748667530948296e-05, "logit_excluded_loss_freq_8_rep": 1.421809431476402e-06, "logit_restricted_loss_freq_8_rep": 4.7701634839614675, "percent_x_embed_freq_8_rep": 2.0080775357200764e-05, "percent_y_embed_freq_8_rep": 3.0214843718567863e-05, "percent_unembed_freq_8_rep": 0.0001462939690100029, "percent_hidden_x_freq_8_rep": 1.6173698895727284e-05, "percent_hidden_y_freq_8_rep": 2.0182200387353078e-05, "percent_hidden_xy_freq_8_rep": 5.901549229747616e-06, "total_percent_hidden_freq_8_rep": 4.2257452150806785e-05, "hidden_excluded_loss_freq_8_rep": 1.4217471168244778e-06, "hidden_restricted_loss_freq_8_rep": 4.770278768098156, "logit_freq_9_rep_trace_similarity": 4.8052475904114544e-05, "logit_excluded_loss_freq_9_rep": 1.4223260448700178e-06, "logit_restricted_loss_freq_9_rep": 4.7699639790736015, "percent_x_embed_freq_9_rep": 3.1596948247170076e-05, "percent_y_embed_freq_9_rep": 8.323791553266346e-05, "percent_unembed_freq_9_rep": 0.0002209639351349324, "percent_hidden_x_freq_9_rep": 1.9163229808327742e-05, "percent_hidden_y_freq_9_rep": 3.561394987627864e-05, "percent_hidden_xy_freq_9_rep": 1.392834383295849e-05, "total_percent_hidden_freq_9_rep": 6.870552169857547e-05, "hidden_excluded_loss_freq_9_rep": 1.4222764453730783e-06, "hidden_restricted_loss_freq_9_rep": 4.77007225098717, "logit_freq_10_rep_trace_similarity": 0.26380693912506104, "logit_excluded_loss_freq_10_rep": 0.0005489202306094268, "logit_restricted_loss_freq_10_rep": 2.5963318055589024, "percent_x_embed_freq_10_rep": 0.16488778591156006, "percent_y_embed_freq_10_rep": 0.16902294754981995, "percent_unembed_freq_10_rep": 0.16269546747207642, "percent_hidden_x_freq_10_rep": 0.06103585660457611, "percent_hidden_y_freq_10_rep": 0.06200871244072914, "percent_hidden_xy_freq_10_rep": 0.01819976419210434, "total_percent_hidden_freq_10_rep": 0.1412443220615387, "hidden_excluded_loss_freq_10_rep": 0.0005527079028203542, "hidden_restricted_loss_freq_10_rep": 2.59886763504525, "logit_freq_11_rep_trace_similarity": 3.9000042306724936e-05, "logit_excluded_loss_freq_11_rep": 1.4222224825206616e-06, "logit_restricted_loss_freq_11_rep": 4.770099728963169, "percent_x_embed_freq_11_rep": 3.550967085175216e-05, "percent_y_embed_freq_11_rep": 1.6470439732074738e-05, "percent_unembed_freq_11_rep": 0.00026490772143006325, "percent_hidden_x_freq_11_rep": 1.727197195577901e-05, "percent_hidden_y_freq_11_rep": 1.016555142996367e-05, "percent_hidden_xy_freq_11_rep": 4.920460014545824e-06, "total_percent_hidden_freq_11_rep": 3.2357984309783205e-05, "hidden_excluded_loss_freq_11_rep": 1.4217248370899798e-06, "hidden_restricted_loss_freq_11_rep": 4.770298362258684, "logit_freq_12_rep_trace_similarity": 0.002691942499950528, "logit_excluded_loss_freq_12_rep": 1.470607850512451e-06, "logit_restricted_loss_freq_12_rep": 4.730513556381582, "percent_x_embed_freq_12_rep": 5.826269625686109e-05, "percent_y_embed_freq_12_rep": 3.2372656278312206e-05, "percent_unembed_freq_12_rep": 0.0018229989800602198, "percent_hidden_x_freq_12_rep": 0.00032898891367949545, "percent_hidden_y_freq_12_rep": 0.00031882902840152383, "percent_hidden_xy_freq_12_rep": 0.00018847263709176332, "total_percent_hidden_freq_12_rep": 0.0008362905937246978, "hidden_excluded_loss_freq_12_rep": 1.4703323790402122e-06, "hidden_restricted_loss_freq_12_rep": 4.730813885448937, "logit_freq_13_rep_trace_similarity": -0.00016529839194845408, "logit_excluded_loss_freq_13_rep": 1.4174018717408e-06, "logit_restricted_loss_freq_13_rep": 4.7731646044360225, "percent_x_embed_freq_13_rep": 1.4132438082015142e-05, "percent_y_embed_freq_13_rep": 1.709214848233387e-05, "percent_unembed_freq_13_rep": 0.00025934676523320377, "percent_hidden_x_freq_13_rep": 2.9009604986640625e-05, "percent_hidden_y_freq_13_rep": 1.550510205561295e-05, "percent_hidden_xy_freq_13_rep": 5.294929724186659e-05, "total_percent_hidden_freq_13_rep": 9.746400610310957e-05, "hidden_excluded_loss_freq_13_rep": 1.4171825487053595e-06, "hidden_restricted_loss_freq_13_rep": 4.773518059667825, "logit_freq_14_rep_trace_similarity": 4.458765033632517e-05, "logit_excluded_loss_freq_14_rep": 1.4221279651809927e-06, "logit_restricted_loss_freq_14_rep": 4.770015936919826, "percent_x_embed_freq_14_rep": 1.2971471733180806e-05, "percent_y_embed_freq_14_rep": 1.0902869689743966e-05, "percent_unembed_freq_14_rep": 0.00019011329277418554, "percent_hidden_x_freq_14_rep": 8.9946152002085e-05, "percent_hidden_y_freq_14_rep": 8.752260328037664e-05, "percent_hidden_xy_freq_14_rep": 2.9098173399688676e-05, "total_percent_hidden_freq_14_rep": 0.0002065669250441715, "hidden_excluded_loss_freq_14_rep": 1.4220159038749214e-06, "hidden_restricted_loss_freq_14_rep": 4.770234206401659, "logit_freq_15_rep_trace_similarity": 5.788429552922025e-05, "logit_excluded_loss_freq_15_rep": 1.4226197695826127e-06, "logit_restricted_loss_freq_15_rep": 4.769816546761502, "percent_x_embed_freq_15_rep": 1.876359965535812e-05, "percent_y_embed_freq_15_rep": 1.7162170479423366e-05, "percent_unembed_freq_15_rep": 0.00029744268977083266, "percent_hidden_x_freq_15_rep": 1.1675418136292137e-05, "percent_hidden_y_freq_15_rep": 1.1642563549685292e-05, "percent_hidden_xy_freq_15_rep": 7.078102498780936e-06, "total_percent_hidden_freq_15_rep": 3.0396084184758365e-05, "hidden_excluded_loss_freq_15_rep": 1.4225278542250537e-06, "hidden_restricted_loss_freq_15_rep": 4.76998467396876, "logit_freq_16_rep_trace_similarity": 1.6499689081683755e-07, "logit_excluded_loss_freq_16_rep": 1.4212159497469562e-06, "logit_restricted_loss_freq_16_rep": 4.770682149776829, "percent_x_embed_freq_16_rep": 3.3207670639967546e-05, "percent_y_embed_freq_16_rep": 1.4545297744916752e-05, "percent_unembed_freq_16_rep": 0.00021064563770778477, "percent_hidden_x_freq_16_rep": 1.6730329662095755e-05, "percent_hidden_y_freq_16_rep": 1.1244834240642376e-05, "percent_hidden_xy_freq_16_rep": 4.2574743019940797e-07, "total_percent_hidden_freq_16_rep": 2.8400911105563864e-05, "hidden_excluded_loss_freq_16_rep": 1.4212161289897456e-06, "hidden_restricted_loss_freq_16_rep": 4.770691558169534, "logit_freq_17_rep_trace_similarity": 6.318152736639604e-05, "logit_excluded_loss_freq_17_rep": 1.4229645349730927e-06, "logit_restricted_loss_freq_17_rep": 4.769737114774642, "percent_x_embed_freq_17_rep": 5.665901699103415e-05, "percent_y_embed_freq_17_rep": 6.341066909953952e-05, "percent_unembed_freq_17_rep": 0.0003416801046114415, "percent_hidden_x_freq_17_rep": 3.841611760435626e-05, "percent_hidden_y_freq_17_rep": 2.7914513339055702e-05, "percent_hidden_xy_freq_17_rep": 5.909485480515286e-05, "total_percent_hidden_freq_17_rep": 0.00012542548938654363, "hidden_excluded_loss_freq_17_rep": 1.4220575982447223e-06, "hidden_restricted_loss_freq_17_rep": 4.7701783734879575, "logit_freq_18_rep_trace_similarity": 0.3438255786895752, "logit_excluded_loss_freq_18_rep": 0.001491107616642942, "logit_restricted_loss_freq_18_rep": 2.3971810650404195, "percent_x_embed_freq_18_rep": 0.25975048542022705, "percent_y_embed_freq_18_rep": 0.25623926520347595, "percent_unembed_freq_18_rep": 0.1839674711227417, "percent_hidden_x_freq_18_rep": 0.09615495055913925, "percent_hidden_y_freq_18_rep": 0.09393437206745148, "percent_hidden_xy_freq_18_rep": 0.027535269036889076, "total_percent_hidden_freq_18_rep": 0.21762458980083466, "hidden_excluded_loss_freq_18_rep": 0.0014960836742447842, "hidden_restricted_loss_freq_18_rep": 2.4009088389691646, "logit_freq_19_rep_trace_similarity": 0.3710963726043701, "logit_excluded_loss_freq_19_rep": 0.0018290894902676426, "logit_restricted_loss_freq_19_rep": 2.3471455600002122, "percent_x_embed_freq_19_rep": 0.2748818099498749, "percent_y_embed_freq_19_rep": 0.27183759212493896, "percent_unembed_freq_19_rep": 0.1999974399805069, "percent_hidden_x_freq_19_rep": 0.10174527764320374, "percent_hidden_y_freq_19_rep": 0.09970764070749283, "percent_hidden_xy_freq_19_rep": 0.029459500685334206, "total_percent_hidden_freq_19_rep": 0.23091241717338562, "hidden_excluded_loss_freq_19_rep": 0.0018431431990294407, "hidden_restricted_loss_freq_19_rep": 2.351392707502227, "logit_freq_20_rep_trace_similarity": 0.010880145244300365, "logit_excluded_loss_freq_20_rep": 1.6695633034111966e-06, "logit_restricted_loss_freq_20_rep": 4.610828490574095, "percent_x_embed_freq_20_rep": 1.1437960893090349e-05, "percent_y_embed_freq_20_rep": 1.1763854672608431e-05, "percent_unembed_freq_20_rep": 0.007506602443754673, "percent_hidden_x_freq_20_rep": 0.0018162853084504604, "percent_hidden_y_freq_20_rep": 0.0018476706463843584, "percent_hidden_xy_freq_20_rep": 0.0006915373960509896, "total_percent_hidden_freq_20_rep": 0.00435549346730113, "hidden_excluded_loss_freq_20_rep": 1.6710174399564815e-06, "hidden_restricted_loss_freq_20_rep": 4.613267896104456, "logit_freq_21_rep_trace_similarity": 0.023123834282159805, "logit_excluded_loss_freq_21_rep": 2.139591635946645e-06, "logit_restricted_loss_freq_21_rep": 4.4388994659293575, "percent_x_embed_freq_21_rep": 1.0687455869629048e-05, "percent_y_embed_freq_21_rep": 2.0060288079548627e-05, "percent_unembed_freq_21_rep": 0.01991349831223488, "percent_hidden_x_freq_21_rep": 0.0031794181559234858, "percent_hidden_y_freq_21_rep": 0.0030631469562649727, "percent_hidden_xy_freq_21_rep": 0.0011663875775411725, "total_percent_hidden_freq_21_rep": 0.0074089523404836655, "hidden_excluded_loss_freq_21_rep": 2.143607544086111e-06, "hidden_restricted_loss_freq_21_rep": 4.448816938477688, "logit_freq_22_rep_trace_similarity": -4.2060037230839953e-07, "logit_excluded_loss_freq_22_rep": 1.421206074914349e-06, "logit_restricted_loss_freq_22_rep": 4.770690932803644, "percent_x_embed_freq_22_rep": 1.2300240996410139e-05, "percent_y_embed_freq_22_rep": 2.4097038476611488e-05, "percent_unembed_freq_22_rep": 0.0001751602831063792, "percent_hidden_x_freq_22_rep": 1.077535307558719e-05, "percent_hidden_y_freq_22_rep": 1.5420500858454034e-05, "percent_hidden_xy_freq_22_rep": 2.4281612809318176e-07, "total_percent_hidden_freq_22_rep": 2.643867082952056e-05, "hidden_excluded_loss_freq_22_rep": 1.421201748572237e-06, "hidden_restricted_loss_freq_22_rep": 4.7706959867139975, "logit_freq_23_rep_trace_similarity": 0.024291153997182846, "logit_excluded_loss_freq_23_rep": 2.249692481449316e-06, "logit_restricted_loss_freq_23_rep": 4.422947832996805, "percent_x_embed_freq_23_rep": 0.00025012524565681815, "percent_y_embed_freq_23_rep": 2.3375174350803718e-05, "percent_unembed_freq_23_rep": 0.0234508253633976, "percent_hidden_x_freq_23_rep": 0.003056814894080162, "percent_hidden_y_freq_23_rep": 0.0027943160384893417, "percent_hidden_xy_freq_23_rep": 0.0011076651280745864, "total_percent_hidden_freq_23_rep": 0.006958796177059412, "hidden_excluded_loss_freq_23_rep": 2.2525807336553707e-06, "hidden_restricted_loss_freq_23_rep": 4.433504971918633, "logit_freq_24_rep_trace_similarity": 0.00026319781318306923, "logit_excluded_loss_freq_24_rep": 1.4277776846039384e-06, "logit_restricted_loss_freq_24_rep": 4.76673902611384, "percent_x_embed_freq_24_rep": 1.520205751148751e-05, "percent_y_embed_freq_24_rep": 1.3756777661910746e-05, "percent_unembed_freq_24_rep": 0.0004089224967174232, "percent_hidden_x_freq_24_rep": 8.803533273749053e-05, "percent_hidden_y_freq_24_rep": 8.966749010141939e-05, "percent_hidden_xy_freq_24_rep": 2.582028719189111e-05, "total_percent_hidden_freq_24_rep": 0.00020352311548776925, "hidden_excluded_loss_freq_24_rep": 1.4272722240183784e-06, "hidden_restricted_loss_freq_24_rep": 4.766798282654758, "logit_freq_25_rep_trace_similarity": 1.2399829756759573e-05, "logit_excluded_loss_freq_25_rep": 1.4214681973474917e-06, "logit_restricted_loss_freq_25_rep": 4.77049865116568, "percent_x_embed_freq_25_rep": 1.4660752640338615e-05, "percent_y_embed_freq_25_rep": 1.2424141459632665e-05, "percent_unembed_freq_25_rep": 0.00018495653057470918, "percent_hidden_x_freq_25_rep": 1.1138430636492558e-05, "percent_hidden_y_freq_25_rep": 1.151269952970324e-05, "percent_hidden_xy_freq_25_rep": 3.278523990957183e-06, "total_percent_hidden_freq_25_rep": 2.5929653929779306e-05, "hidden_excluded_loss_freq_25_rep": 1.4214828289151725e-06, "hidden_restricted_loss_freq_25_rep": 4.770533892642193, "logit_freq_26_rep_trace_similarity": 0.2347049117088318, "logit_excluded_loss_freq_26_rep": 0.00013142606334916809, "logit_restricted_loss_freq_26_rep": 2.697958289542839, "percent_x_embed_freq_26_rep": 0.12959030270576477, "percent_y_embed_freq_26_rep": 0.13029098510742188, "percent_unembed_freq_26_rep": 0.15753085911273956, "percent_hidden_x_freq_26_rep": 0.04795483499765396, "percent_hidden_y_freq_26_rep": 0.04776160418987274, "percent_hidden_xy_freq_26_rep": 0.014876020140945911, "total_percent_hidden_freq_26_rep": 0.11059246212244034, "hidden_excluded_loss_freq_26_rep": 0.00013209467717460895, "hidden_restricted_loss_freq_26_rep": 2.700169135762573, "logit_freq_27_rep_trace_similarity": 5.245381544227712e-06, "logit_excluded_loss_freq_27_rep": 1.4213213124257514e-06, "logit_restricted_loss_freq_27_rep": 4.770605952899979, "percent_x_embed_freq_27_rep": 2.0043598851771094e-05, "percent_y_embed_freq_27_rep": 1.1291545888525434e-05, "percent_unembed_freq_27_rep": 0.00017250669770874083, "percent_hidden_x_freq_27_rep": 9.597538337402511e-06, "percent_hidden_y_freq_27_rep": 6.606936040043365e-06, "percent_hidden_xy_freq_27_rep": 8.3624382796188e-07, "total_percent_hidden_freq_27_rep": 1.7040718375938013e-05, "hidden_excluded_loss_freq_27_rep": 1.4212605723244204e-06, "hidden_restricted_loss_freq_27_rep": 4.770629987712013, "logit_freq_28_rep_trace_similarity": -3.746075162780471e-05, "logit_excluded_loss_freq_28_rep": 1.4204383513535853e-06, "logit_restricted_loss_freq_28_rep": 4.771246515291904, "percent_x_embed_freq_28_rep": 0.00023398100165650249, "percent_y_embed_freq_28_rep": 4.819078458240256e-05, "percent_unembed_freq_28_rep": 0.00018468036432750523, "percent_hidden_x_freq_28_rep": 9.382338612340391e-05, "percent_hidden_y_freq_28_rep": 2.4546032364014536e-05, "percent_hidden_xy_freq_28_rep": 2.310240233782679e-05, "total_percent_hidden_freq_28_rep": 0.00014147182810120285, "hidden_excluded_loss_freq_28_rep": 1.4200805434450714e-06, "hidden_restricted_loss_freq_28_rep": 4.771668442067586, "logit_freq_29_rep_trace_similarity": 0.00018394499784335494, "logit_excluded_loss_freq_29_rep": 1.4255288202025208e-06, "logit_restricted_loss_freq_29_rep": 4.767926695048388, "percent_x_embed_freq_29_rep": 0.00012643466470763087, "percent_y_embed_freq_29_rep": 0.00024804146960377693, "percent_unembed_freq_29_rep": 0.00029880928923375905, "percent_hidden_x_freq_29_rep": 5.3510029829340056e-05, "percent_hidden_y_freq_29_rep": 9.462577872909606e-05, "percent_hidden_xy_freq_29_rep": 0.00012540082389023155, "total_percent_hidden_freq_29_rep": 0.00027353662881068885, "hidden_excluded_loss_freq_29_rep": 1.4250657834570153e-06, "hidden_restricted_loss_freq_29_rep": 4.7688880098261, "percent_logits_explained": 0.5492140650749207, "total_logit_excluded_loss": 12.71699949358148, "total_logit_restricted_loss": 1.6229672050599654e-06, "total_hidden_excluded_loss": 12.739849611210925, "total_hidden_restricted_loss": 1.769065766841018e-06, "test_loss_restricted_loss_ratio": 2.4279769588654885, "sum_of_squared_weights": 5065.22265625, "percent_hidden_explained": 0.8805485963821411, "percent_hidden_xy_explained": 0.12659992277622223, "percent_x_embed_explained": 0.999047040939331, "percent_y_embed_explained": 0.9992631673812866, "percent_unembed_explained": 0.9857432246208191, "epoch": 250000.0}